geezlit/__init__.py
geezlit/cli.py
geezlit/lit.py
geezlit/py.typed
geezlit/version.py
geezlit/style/__init__.py
geezlit/style/base.py
geezlit/style/ethiop.py
geezlit/style/geezime.py
geezlit/style/ipa.py
geezlit/style/msera.py
geezlit/style/sera.py
geezlit-0.1.5.dist-info/LICENSE
geezlit-0.1.5.dist-info/METADATA
geezlit-0.1.5.dist-info/WHEEL
geezlit-0.1.5.dist-info/entry_points.txt
geezlit-0.1.5.dist-info/top_level.txt
geezlit-0.1.5.dist-info/RECORD
